README.rst
setup.py
wls_rest_python.py
wls_rest_python.egg-info/PKG-INFO
wls_rest_python.egg-info/SOURCES.txt
wls_rest_python.egg-info/dependency_links.txt
wls_rest_python.egg-info/requires.txt
wls_rest_python.egg-info/top_level.txt