Metadata-Version: 1.1
Name: wls-rest-python
Version: 0.1.1
Summary: A Python client for the Weblogic REST API
Home-page: https://github.com/magnuswatn/wls-rest-python
Author: Magnus Watn
Author-email: UNKNOWN
License: MIT
Keywords: weblogic wls rest administration automation
Platform: UNKNOWN
Classifier: Development Status :: 4 - Beta
Classifier: Intended Audience :: Developers
Classifier: Intended Audience :: System Administrators
Classifier: License :: OSI Approved :: MIT License
Classifier: Topic :: System :: Systems Administration
Classifier: Programming Language :: Python :: 2
Classifier: Programming Language :: Python :: 2.7
Classifier: Programming Language :: Python :: 3
Classifier: Programming Language :: Python :: 3.4
Classifier: Programming Language :: Python :: 3.5
Classifier: Programming Language :: Python :: 3.6
